{
    "sourceFile": "package.json",
    "activeCommit": 0,
    "commits": [
        {
            "activePatchIndex": 2,
            "patches": [
                {
                    "date": 1715789216046,
                    "content": "Index: \n===================================================================\n--- \n+++ \n"
                },
                {
                    "date": 1715845953589,
                    "content": "Index: \n===================================================================\n--- \n+++ \n@@ -5,21 +5,46 @@\n   \"author\": \"sayhi.kenan@gmail.com\",\n   \"type\": \"module\",\n   \"scripts\": {\n     \"build\": \"tsc && vite build\",\n+    \"build-storybook\": \"storybook build\",\n     \"lint\": \"eslint . --ext ts,tsx --report-unused-disable-directives --max-warnings 0\",\n     \"start\": \"pnpm run start:dev\",\n     \"start:dev\": \"vite\",\n     \"start:preview\": \"vite preview\",\n+    \"storybook\": \"storybook dev -p 6006\",\n     \"test\": \"vitest --run\",\n     \"test:ui\": \"vitest --ui\"\n   },\n   \"dependencies\": {\n+    \"@radix-ui/react-dialog\": \"^1.0.5\",\n+    \"@radix-ui/react-popover\": \"^1.0.7\",\n+    \"@radix-ui/react-slot\": \"^1.0.2\",\n+    \"@tanstack/react-query\": \"^5.36.2\",\n+    \"@tanstack/react-query-devtools\": \"^5.36.2\",\n     \"class-variance-authority\": \"^0.7.0\",\n+    \"clsx\": \"^2.1.1\",\n+    \"cmdk\": \"^1.0.0\",\n+    \"lucide-react\": \"^0.378.0\",\n     \"react\": \"^18.3.1\",\n-    \"react-dom\": \"^18.3.1\"\n+    \"react-dom\": \"^18.3.1\",\n+    \"tailwind-merge\": \"^2.3.0\",\n+    \"tailwindcss-animate\": \"^1.0.7\",\n+    \"zustand\": \"^4.5.2\"\n   },\n   \"devDependencies\": {\n+    \"@chromatic-com/storybook\": \"^1.4.0\",\n+    \"@storybook/addon-actions\": \"^8.1.1\",\n+    \"@storybook/addon-docs\": \"^8.1.1\",\n+    \"@storybook/addon-essentials\": \"^8.1.1\",\n+    \"@storybook/addon-interactions\": \"^8.1.1\",\n+    \"@storybook/addon-links\": \"^8.1.1\",\n+    \"@storybook/addon-onboarding\": \"^8.1.1\",\n+    \"@storybook/blocks\": \"^8.1.1\",\n+    \"@storybook/preview-api\": \"^8.1.1\",\n+    \"@storybook/react\": \"^8.1.1\",\n+    \"@storybook/react-vite\": \"^8.1.1\",\n+    \"@storybook/test\": \"^8.1.1\",\n     \"@testing-library/jest-dom\": \"^6.4.5\",\n     \"@testing-library/react\": \"^15.0.7\",\n     \"@testing-library/user-event\": \"^14.5.2\",\n     \"@types/node\": \"^20.12.12\",\n@@ -29,8 +54,9 @@\n     \"@typescript-eslint/parser\": \"^7.9.0\",\n     \"@vitejs/plugin-react-swc\": \"^3.6.0\",\n     \"@vitest/ui\": \"^1.6.0\",\n     \"autoprefixer\": \"^10.4.19\",\n+    \"axios\": \"^1.6.8\",\n     \"eslint\": \"^8.57.0\",\n     \"eslint-config-prettier\": \"^9.1.0\",\n     \"eslint-import-resolver-typescript\": \"^3.6.1\",\n     \"eslint-plugin-import\": \"^2.29.1\",\n@@ -38,14 +64,16 @@\n     \"eslint-plugin-jsx-a11y\": \"^6.8.0\",\n     \"eslint-plugin-react\": \"^7.34.1\",\n     \"eslint-plugin-react-hooks\": \"^4.6.2\",\n     \"eslint-plugin-react-refresh\": \"^0.4.7\",\n+    \"eslint-plugin-storybook\": \"^0.8.0\",\n     \"eslint-plugin-tailwindcss\": \"^3.15.1\",\n     \"eslint-plugin-testing-library\": \"^6.2.2\",\n     \"eslint-plugin-vitest\": \"^0.5.4\",\n     \"happy-dom\": \"^14.11.0\",\n     \"postcss\": \"^8.4.38\",\n     \"prettier\": \"^3.2.5\",\n+    \"storybook\": \"^8.1.1\",\n     \"tailwindcss\": \"^3.4.3\",\n     \"typescript\": \"^5.4.5\",\n     \"vite\": \"^5.2.11\",\n     \"vite-tsconfig-paths\": \"^4.3.2\",\n"
                },
                {
                    "date": 1715967344102,
                    "content": "Index: \n===================================================================\n--- \n+++ \n@@ -16,8 +16,9 @@\n     \"test:ui\": \"vitest --ui\"\n   },\n   \"dependencies\": {\n     \"@radix-ui/react-dialog\": \"^1.0.5\",\n+    \"@radix-ui/react-label\": \"^2.0.2\",\n     \"@radix-ui/react-popover\": \"^1.0.7\",\n     \"@radix-ui/react-slot\": \"^1.0.2\",\n     \"@tanstack/react-query\": \"^5.36.2\",\n     \"@tanstack/react-query-devtools\": \"^5.36.2\",\n@@ -26,10 +27,12 @@\n     \"cmdk\": \"^1.0.0\",\n     \"lucide-react\": \"^0.378.0\",\n     \"react\": \"^18.3.1\",\n     \"react-dom\": \"^18.3.1\",\n+    \"react-router-dom\": \"^6.23.1\",\n     \"tailwind-merge\": \"^2.3.0\",\n     \"tailwindcss-animate\": \"^1.0.7\",\n+    \"use-debounce\": \"^10.0.0\",\n     \"zustand\": \"^4.5.2\"\n   },\n   \"devDependencies\": {\n     \"@chromatic-com/storybook\": \"^1.4.0\",\n@@ -64,10 +67,11 @@\n     \"eslint-plugin-jsx-a11y\": \"^6.8.0\",\n     \"eslint-plugin-react\": \"^7.34.1\",\n     \"eslint-plugin-react-hooks\": \"^4.6.2\",\n     \"eslint-plugin-react-refresh\": \"^0.4.7\",\n+    \"eslint-plugin-readable-tailwind\": \"^1.3.2\",\n     \"eslint-plugin-storybook\": \"^0.8.0\",\n-    \"eslint-plugin-tailwindcss\": \"^3.15.1\",\n+    \"eslint-plugin-tailwindcss\": \"^3.15.2\",\n     \"eslint-plugin-testing-library\": \"^6.2.2\",\n     \"eslint-plugin-vitest\": \"^0.5.4\",\n     \"happy-dom\": \"^14.11.0\",\n     \"postcss\": \"^8.4.38\",\n"
                }
            ],
            "date": 1715789216046,
            "name": "Commit-0",
            "content": "{\n  \"name\": \"weather-app\",\n  \"version\": \"0.0.0\",\n  \"private\": true,\n  \"author\": \"sayhi.kenan@gmail.com\",\n  \"type\": \"module\",\n  \"scripts\": {\n    \"build\": \"tsc && vite build\",\n    \"lint\": \"eslint . --ext ts,tsx --report-unused-disable-directives --max-warnings 0\",\n    \"start\": \"pnpm run start:dev\",\n    \"start:dev\": \"vite\",\n    \"start:preview\": \"vite preview\",\n    \"test\": \"vitest --run\",\n    \"test:ui\": \"vitest --ui\"\n  },\n  \"dependencies\": {\n    \"class-variance-authority\": \"^0.7.0\",\n    \"react\": \"^18.3.1\",\n    \"react-dom\": \"^18.3.1\"\n  },\n  \"devDependencies\": {\n    \"@testing-library/jest-dom\": \"^6.4.5\",\n    \"@testing-library/react\": \"^15.0.7\",\n    \"@testing-library/user-event\": \"^14.5.2\",\n    \"@types/node\": \"^20.12.12\",\n    \"@types/react\": \"^18.3.2\",\n    \"@types/react-dom\": \"^18.3.0\",\n    \"@typescript-eslint/eslint-plugin\": \"^7.9.0\",\n    \"@typescript-eslint/parser\": \"^7.9.0\",\n    \"@vitejs/plugin-react-swc\": \"^3.6.0\",\n    \"@vitest/ui\": \"^1.6.0\",\n    \"autoprefixer\": \"^10.4.19\",\n    \"eslint\": \"^8.57.0\",\n    \"eslint-config-prettier\": \"^9.1.0\",\n    \"eslint-import-resolver-typescript\": \"^3.6.1\",\n    \"eslint-plugin-import\": \"^2.29.1\",\n    \"eslint-plugin-jest-dom\": \"^5.4.0\",\n    \"eslint-plugin-jsx-a11y\": \"^6.8.0\",\n    \"eslint-plugin-react\": \"^7.34.1\",\n    \"eslint-plugin-react-hooks\": \"^4.6.2\",\n    \"eslint-plugin-react-refresh\": \"^0.4.7\",\n    \"eslint-plugin-tailwindcss\": \"^3.15.1\",\n    \"eslint-plugin-testing-library\": \"^6.2.2\",\n    \"eslint-plugin-vitest\": \"^0.5.4\",\n    \"happy-dom\": \"^14.11.0\",\n    \"postcss\": \"^8.4.38\",\n    \"prettier\": \"^3.2.5\",\n    \"tailwindcss\": \"^3.4.3\",\n    \"typescript\": \"^5.4.5\",\n    \"vite\": \"^5.2.11\",\n    \"vite-tsconfig-paths\": \"^4.3.2\",\n    \"vitest\": \"^1.6.0\"\n  }\n}\n"
        }
    ]
}